LICENSE
MANIFEST.in
README.rst
requirements.txt
setup.py
django_vintage.egg-info/PKG-INFO
django_vintage.egg-info/SOURCES.txt
django_vintage.egg-info/dependency_links.txt
django_vintage.egg-info/pbr.json
django_vintage.egg-info/requires.txt
django_vintage.egg-info/top_level.txt
doc_src/.DS_Store
doc_src/Makefile
doc_src/conf.py
doc_src/getting_started.rst
doc_src/index.rst
doc_src/make.bat
doc_src/metadata.rst
doc_src/templates.rst
doc_src/_build/doctrees/environment.pickle
doc_src/_build/doctrees/getting_started.doctree
doc_src/_build/doctrees/index.doctree
doc_src/_build/doctrees/installation.doctree
doc_src/_build/doctrees/metadata.doctree
doc_src/_build/doctrees/templates.doctree
doc_src/_build/doctrees/reference/archiveurl.doctree
doc_src/_build/doctrees/reference/index.doctree
doc_src/_build/doctrees/reference/models.doctree
doc_src/_build/doctrees/reference/settings.doctree
doc_src/_static/breadcrumb_background.png
doc_src/_static/default.css
doc_src/_static/documentation.png
doc_src/_static/header_sm_mid.png
doc_src/_static/scrn1.png
doc_src/_static/scrn2.png
doc_src/_static/searchfield_leftcap.png
doc_src/_static/searchfield_repeat.png
doc_src/_static/searchfield_rightcap.png
doc_src/_static/title_background.png
doc_src/_static/toc.js
doc_src/_static/triangle_closed.png
doc_src/_static/triangle_left.png
doc_src/_static/triangle_open.png
doc_src/_templates/layout.html
doc_src/includes/default_tmpl.html
doc_src/includes/demo_import.py
doc_src/reference/archiveurl.rst
doc_src/reference/index.rst
doc_src/reference/models.rst
doc_src/reference/settings.rst
docs/.buildinfo
docs/genindex.html
docs/getting_started.html
docs/index.html
docs/installation.html
docs/metadata.html
docs/objects.inv
docs/search.html
docs/searchindex.js
docs/templates.html
docs/_sources/getting_started.txt
docs/_sources/index.txt
docs/_sources/installation.txt
docs/_sources/metadata.txt
docs/_sources/templates.txt
docs/_sources/reference/archiveurl.txt
docs/_sources/reference/index.txt
docs/_sources/reference/models.txt
docs/_sources/reference/settings.txt
docs/_static/basic.css
docs/_static/breadcrumb_background.png
docs/_static/default.css
docs/_static/doctools.js
docs/_static/documentation.png
