Metadata-Version: 1.1
Name: django-vintage
Version: 0.3
Summary: An archiver of web pages. Like a specialized django-flatpages.
Home-page: http://callowayproject.com/projects/
Author: coordt
Author-email: coreyoordt@gmail.com
License: UNKNOWN
Platform: UNKNOWN
Classifier: License :: OSI Approved :: Apache Software License
Classifier: Framework :: Django
